LICENSE.txt
MANIFEST.in
README.rst
requirements.txt
setup.py
drclip/__init__.py
drclip/__version__.py
drclip/cmds.py
drclip/creds.py
drclip/drapi.py
drclip.egg-info/PKG-INFO
drclip.egg-info/SOURCES.txt
drclip.egg-info/dependency_links.txt
drclip.egg-info/entry_points.txt
drclip.egg-info/requires.txt
drclip.egg-info/top_level.txt
tests/__init__.py
tests/conftest.py
tests/mocks.py
tests/test_cmds.py
tests/test_creds.py
tests/test_drapi.py