Metadata-Version: 2.1
Name: drclip
Version: 2.0.2
Summary: A click based tool for working with remote docker registries
Home-page: UNKNOWN
Author: Jim Carreer
Author-email: jim.carreer+drclip@gmail.com
License: ISC License
Platform: UNKNOWN
Classifier: Environment :: Console
Requires-Python: >3.6.0
Provides-Extra: tests
